[
  {
    "line": 1,
    "elements": [
      {
        "start_timestamp": "2020-04-21T16:40:22.766Z",
        "line": 3,
        "name": "Free CRM Login page",
        "description": "",
        "id": "free-crm-login;free-crm-login-page",
        "type": "scenario",
        "keyword": "Scenario",
        "steps": [
          {
            "result": {
              "duration": 8826000000,
              "status": "passed"
            },
            "line": 4,
            "name": "User is already login page",
            "match": {
              "location": "stepDefinition.OrangeHRMSteps.user_is_already_login_page()"
            },
            "keyword": "Given "
          },
          {
            "result": {
              "duration": 793000000,
              "status": "passed"
            },
            "line": 5,
            "name": "Title of the login page is Free CRM",
            "match": {
              "location": "stepDefinition.OrangeHRMSteps.title_of_the_login_page_is_Free_CRM()"
            },
            "keyword": "When "
          },
          {
            "result": {
              "duration": 10151000000,
              "status": "passed"
            },
            "line": 6,
            "name": "user enters \"Vishal\" and \"password\"",
            "match": {
              "arguments": [
                {
                  "val": "Vishal",
                  "offset": 13
                },
                {
                  "val": "password",
                  "offset": 26
                }
              ],
              "location": "stepDefinition.OrangeHRMSteps.user_enters_username_password(java.lang.String,java.lang.String)"
            },
            "keyword": "Then "
          },
          {
            "result": {
              "duration": 189000000,
              "status": "passed"
            },
            "line": 7,
            "name": "user clicks on login button",
            "match": {
              "location": "stepDefinition.OrangeHRMSteps.user_clicks_on_login_button()"
            },
            "keyword": "Then "
          },
          {
            "result": {
              "duration": 2000000,
              "status": "passed"
            },
            "line": 8,
            "name": "user is on home page",
            "match": {
              "location": "stepDefinition.OrangeHRMSteps.user_is_on_home_page()"
            },
            "keyword": "Then "
          },
          {
            "result": {
              "duration": 718000000,
              "status": "passed"
            },
            "line": 9,
            "name": "close the browser",
            "match": {
              "location": "stepDefinition.OrangeHRMSteps.close_the_browser()"
            },
            "keyword": "Then "
          }
        ]
      }
    ],
    "name": "Free CRM Login",
    "description": "",
    "id": "free-crm-login",
    "keyword": "Feature",
    "uri": "file:features/OrangeHRM.feature",
    "tags": []
  }
]